covjson_pydantic/__init__.py
covjson_pydantic/base_models.py
covjson_pydantic/coverage.py
covjson_pydantic/domain.py
covjson_pydantic/i18n.py
covjson_pydantic/ndarray.py
covjson_pydantic/observed_property.py
covjson_pydantic/parameter.py
covjson_pydantic/py.typed
covjson_pydantic/reference_system.py
covjson_pydantic/unit.py
covjson_pydantic-0.6.0.dist-info/licenses/LICENSE
covjson_pydantic-0.6.0.dist-info/WHEEL
covjson_pydantic-0.6.0.dist-info/METADATA
covjson_pydantic-0.6.0.dist-info/RECORD
