Metadata-Version: 2.4
Name: covjson-pydantic
Version: 0.6.0
Summary: The Pydantic models for CoverageJSON
Keywords: covjson,Pydantic
Author-email: KNMI Data Platform Team <opendata@knmi.nl>
Requires-Python: >=3.8
Classifier: Intended Audience :: Information Technology
Classifier: Intended Audience :: Science/Research
Classifier: License :: OSI Approved :: Apache Software License
Classifier: Programming Language :: Python :: 3.8
Classifier: Programming Language :: Python :: 3.9
Classifier: Programming Language :: Python :: 3.10
Classifier: Programming Language :: Python :: 3.11
Classifier: Programming Language :: Python :: 3.12
Classifier: Programming Language :: Python :: 3.13
Classifier: Topic :: Scientific/Engineering :: GIS
Classifier: Typing :: Typed
License-File: LICENSE
Requires-Dist: pydantic>=2.3,<3
Requires-Dist: pre-commit ; extra == "dev"
Requires-Dist: pytest ; extra == "test"
Requires-Dist: pytest-cov ; extra == "test"
Project-URL: Source, https://github.com/knmi/covjson-pydantic
Provides-Extra: dev
Provides-Extra: test
